lmcache_frontend/.DS_Store
lmcache_frontend/__init__.py
lmcache_frontend/app.py
lmcache_frontend/config.json
lmcache_frontend/heartbeat.py
lmcache_frontend/simple_discover_service.py
lmcache_frontend/__pycache__/__init__.cpython-312.pyc
lmcache_frontend/__pycache__/app.cpython-312.pyc
lmcache_frontend/__pycache__/heartbeat.cpython-312.pyc
lmcache_frontend/lmcache_plugin/scheduler_lmc_frontend_plugin.py
lmcache_frontend/static/.DS_Store
lmcache_frontend/static/index.html
lmcache_frontend/static/css/style.css
lmcache_frontend/static/img/logo.png
lmcache_frontend/static/js/app.js
lmcache_frontend-0.1.12.dist-info/METADATA
lmcache_frontend-0.1.12.dist-info/WHEEL
lmcache_frontend-0.1.12.dist-info/entry_points.txt
lmcache_frontend-0.1.12.dist-info/top_level.txt
lmcache_frontend-0.1.12.dist-info/RECORD
