Metadata-Version: 2.4
Name: lmcache_frontend
Version: 0.1.12
Requires-Dist: Flask
Requires-Dist: setuptools>=77.0.3
Requires-Dist: packaging>=24.2
Requires-Dist: setuptools_scm>=8
Requires-Dist: wheel
Requires-Dist: fastapi
Requires-Dist: uvicorn
Requires-Dist: httpx
Requires-Dist: starlette
Dynamic: requires-dist
